customs/__init__.py
customs/customs.py
customs/exceptions.py
customs/helpers.py
customs/strategies/__init__.py
customs/strategies/base_strategy.py
customs/strategies/basic_strategy.py
customs/strategies/facebook_strategy.py
customs/strategies/github_strategy.py
customs/strategies/google_strategy.py
customs/strategies/jwt_strategy.py
customs/strategies/local_strategy.py
customs/strategies/oauth2_strategy.py
tests/__init__.py
tests/test_exceptions.py
tests/test_helpers.py
customs-0.5.0.dist-info/LICENSE.md
customs-0.5.0.dist-info/METADATA
customs-0.5.0.dist-info/WHEEL
customs-0.5.0.dist-info/top_level.txt
customs-0.5.0.dist-info/RECORD
