Metadata-Version: 2.1
Name: customs
Version: 0.5.0
Summary: Python library for guarding APIs.
Home-page: https://github.com/gijswobben/customs
Author: NewInnovator
Author-email: 
License: MIT
Keywords: Security Flask Authentication
Platform: UNKNOWN
Classifier: Topic :: Utilities
Classifier: Development Status :: 3 - Alpha
Classifier: License :: OSI Approved :: MIT License
Classifier: Programming Language :: Python :: 3 :: Only
Classifier: Programming Language :: Python :: 3.7
Classifier: Programming Language :: Python :: 3.8
Classifier: Programming Language :: Python :: 3.9
Classifier: Operating System :: OS Independent
Requires-Python: >=3.7
Provides-Extra: test
